ProjectAlice/__init__.py
ProjectAlice/core/Initializer.py
ProjectAlice/core/__init__.py
ProjectAlice/core/base/__init__.py
ProjectAlice/core/base/model/Version.py
ProjectAlice/core/base/model/__init__.py
ProjectAlice/core/commons/CommonsManager.py
ProjectAlice/core/commons/__init__.py
ProjectAlice/core/commons/constants.py
ProjectAlice/core/commons/model/PartOfDay.py
ProjectAlice/core/commons/model/Singleton.py
ProjectAlice/core/commons/model/Slot.py
ProjectAlice/core/commons/model/__init__.py
ProjectAlice-0.0.3.dist-info/LICENSE
ProjectAlice-0.0.3.dist-info/METADATA
ProjectAlice-0.0.3.dist-info/WHEEL
ProjectAlice-0.0.3.dist-info/top_level.txt
ProjectAlice-0.0.3.dist-info/RECORD
