Metadata-Version: 2.1
Name: ProjectAlice
Version: 0.0.3
Summary: Project Alice universal modules
Home-page: https://github.com/project-alice-assistant/ProjectAliceCommons
Author: ProjectAlice
Author-email: laurentchervet@bluewin.ch
Maintainer: Psychokiller1888
License: GPL-3.0
Platform: UNKNOWN
Classifier: Development Status :: 1 - Planning
Classifier: Intended Audience :: Developers
Classifier: License :: OSI Approved :: GNU General Public License v3 (GPLv3)
Classifier: Operating System :: OS Independent
Classifier: Programming Language :: Python :: 3.7
Classifier: Topic :: Home Automation
Requires-Python: >=3.7
